LICENSE.md
MANIFEST.in
README.md
setup.py
django_api_gen/__init__.py
django_api_gen/manager.py
django_api_gen/util.py
django_api_gen/api/__init__.py
django_api_gen/api/serializers.py
django_api_gen/api/urls.py
django_api_gen/api/views.py
django_api_gen/management/__init__.py
django_api_gen/management/commands/__init__.py
django_api_gen/management/commands/generate-api.py
django_api_gen/serializers/__init__.py
django_api_gen/serializers/base_imports
django_api_gen/serializers/base_serializer
django_api_gen/serializers/library_imports
django_api_gen/serializers/serializers_structure
django_api_gen/urls/__init__.py
django_api_gen/urls/base_imports
django_api_gen/urls/base_urls_path
django_api_gen/urls/library_imports
django_api_gen/urls/urls_structure
django_api_gen/views/__init__.py
django_api_gen/views/base_imports
django_api_gen/views/base_views
django_api_gen/views/library_imports
django_api_gen/views/views_structure
django_api_generator.egg-info/PKG-INFO
django_api_generator.egg-info/SOURCES.txt
django_api_generator.egg-info/dependency_links.txt
django_api_generator.egg-info/not-zip-safe
django_api_generator.egg-info/requires.txt
django_api_generator.egg-info/top_level.txt
docs/blank.txt